airgap_sak/backup.py
airgap-0.1.0.dist-info/LICENSE
airgap-0.1.0.dist-info/METADATA
airgap-0.1.0.dist-info/WHEEL
airgap-0.1.0.dist-info/entry_points.txt
airgap-0.1.0.dist-info/top_level.txt
airgap-0.1.0.dist-info/RECORD
